{
  "items": [
    {
      "id": 1234,
      "name": "oak-table",
      "category":"diningroom",
      "type": "table",
      "price": 700,
      "description": "dining_table",
      "dimensions": "W 100cm, L 200cm, H 110cm",
      "stock": 100,
      "colour": "deep oak",
      "image": "image/Dining room.jpg"},

    { "id":4321,
      "name": "oak-table",
      "category":"bedroom",
      "type": "table",
      "price": 900,
      "description": "dining_table",
      "dimensions": "W 100cm, L 200cm, H 110cm",
      "stock": 100,
      "colour": "deep oak",
      "image": "image/Dining room -2.jpg"},

    { "id":2541,
      "name": "oak-chair",
      "type": "chair",
      "category":"office",
      "price": 50,
      "description": "dining_chair",
      "dimensions": "W 100cm, L 200cm, H 110cm",
      "stock": 100,
      "colour": "deep oak",
      "image": "image/Dining room-7.jpg"},

    { "id":2336,
      "name": "oak-Bed",
      "type": "Bed",
      "category":"bedroom",
      "price": 1000,
      "description": "Bed",
      "dimensions": "W 100cm, L 200cm, H 110cm",
      "stock": 100,
      "colour": "deep oak",
      "image": "image/Bedroom.jpg"}



        ]
    }
